tube_checkout/__init__.py
tube_checkout/calibration.py
tube_checkout/hid.py
tube_checkout/hid.pyc
tube_checkout/tube_movement.py
tube_checkout/utils.py
tube_checkout/labware/24_2ml_rack.json
tube_checkout/labware/__init__.py
tube_checkout/labware/__init__.pyc
tube_checkout-0.1.1.2.dist-info/METADATA
tube_checkout-0.1.1.2.dist-info/WHEEL
tube_checkout-0.1.1.2.dist-info/top_level.txt
tube_checkout-0.1.1.2.dist-info/RECORD
