Metadata-Version: 2.1
Name: tube-checkout
Version: 0.1.1.2
Summary: Scan tube barcodes with OpenTrons
Home-page: http://github.com/theosanderson/tubecheckout
Author: Theo Sanderson
Author-email: theo@theo.io
License: MIT
Platform: UNKNOWN
Requires-Dist: opentrons (==3.18.1)
